airflow_utils_test/__init__.py
airflow_utils_test/trends_utils_test.py
zilingo_airflow_utils_test-1.0.5.dist-info/LICENSE
zilingo_airflow_utils_test-1.0.5.dist-info/METADATA
zilingo_airflow_utils_test-1.0.5.dist-info/WHEEL
zilingo_airflow_utils_test-1.0.5.dist-info/top_level.txt
zilingo_airflow_utils_test-1.0.5.dist-info/RECORD
